fabrictesting/__init__.py
fabrictesting/fabric_api/__init__.py
fabrictesting/fabric_api/api_access.py
fabrictesting/notebook/__init__.py
fabrictesting/notebook/create.py
fabrictesting/notebook/get_definitions.py
fabrictesting/notebook/get_notebook_status.py
fabrictesting/notebook/notebook-content.ipynb
fabrictesting/notebook/run.py
fabrictesting/notebook/upload.py
fabrictesting/onelake_api/__init__.py
fabrictesting/onelake_api/api_access.py
fabrictesting/onelake_api/api_file.py
fabrictesting/test_job/__init__.py
fabrictesting/test_job/fetch.py
fabrictesting/test_job/submit.py
fabrictesting/utilities/__init__.py
fabrictesting/utilities/collect.py
fabrictesting/utilities/load_fetch_url_log.py
fabrictesting/utilities/save_fetch_url_log.py
fabrictesting/utilities/validate_args.py
fabric_testing-0.1.0.dist-info/LICENSE
fabric_testing-0.1.0.dist-info/METADATA
fabric_testing-0.1.0.dist-info/WHEEL
fabric_testing-0.1.0.dist-info/entry_points.txt
fabric_testing-0.1.0.dist-info/top_level.txt
fabric_testing-0.1.0.dist-info/RECORD
