Metadata-Version: 2.1
Name: fabric-testing
Version: 0.1.0
Summary: Testing functionalities for Microsoft Fabric
Author: LauJohansson
License: MIT License
Project-URL: Homepage, https://github.com/LauJohansson/fabric-testing
Keywords: Microsoft,Fabric,testing
Classifier: Programming Language :: Python :: 3
Classifier: License :: OSI Approved :: MIT License
Classifier: Operating System :: OS Independent
Requires-Python: >=3.11
License-File: LICENSE
Requires-Dist: setuptools==68.2.0
Requires-Dist: requests==2.32.3
Requires-Dist: pytest==8.3.3
Requires-Dist: azure-storage-file-datalake==12.17.0
Requires-Dist: azure-identity==1.18.0
Provides-Extra: dev
Requires-Dist: ruff; extra == "dev"
Requires-Dist: pytest; extra == "dev"
